sobrecargar/__init__.py
sobrecargar/firma.py
sobrecargar/py.typed
sobrecargar/sobrecargar.py
sobrecargar-4.1.0.dist-info/licenses/LICENSE
sobrecargar-4.1.0.dist-info/METADATA
sobrecargar-4.1.0.dist-info/WHEEL
sobrecargar-4.1.0.dist-info/top_level.txt
sobrecargar-4.1.0.dist-info/RECORD
