Metadata-Version: 2.4
Name: sobrecargar
Version: 4.1.0
Summary: Sobrecarga de métodos y funciones para Python 3.
Home-page: https://github.com/Hernanatn/sobrecargar.py
Download-URL: https://pypi.org/project/sobrecargar/3.1.1/#files
Author: Hernán A. Teszkiewicz Novick
Author-email: "Hernán A.T.N." <herni@cajadeideas.ar>
Project-URL: Homepage, https://github.com/Hernanatn/sobrecargar.py
Classifier: Programming Language :: Python :: 3
Classifier: License :: OSI Approved :: MIT License
Classifier: Operating System :: OS Independent
Requires-Python: >=3.9
License-File: LICENSE
Requires-Dist: typing_extensions; python_version < "3.11"
Dynamic: author
Dynamic: download-url
Dynamic: home-page
Dynamic: license-file
